setup.py
slackbotpy/__init__.py
slackbotpy.egg-info/PKG-INFO
slackbotpy.egg-info/SOURCES.txt
slackbotpy.egg-info/dependency_links.txt
slackbotpy.egg-info/not-zip-safe
slackbotpy.egg-info/top_level.txt