Metadata-Version: 1.0
Name: slackbotpy
Version: 0.1
Summary: Your team slack bot
Home-page: http://github.com/viniciusgama/slackbotpy
Author: Vinicius Gama
Author-email: vinicius.sgama@gmail.com
License: MIT
Platform: UNKNOWN
